LICENSE.txt
README.rst
setup.py
example/Verdana.ttf
example/in.html
example/kanguru.jpg
example/styles.css
inline_html/__init__.py
inline_html/dr.py
inline_html/inline_html.py
inline_html.egg-info/PKG-INFO
inline_html.egg-info/SOURCES.txt
inline_html.egg-info/dependency_links.txt
inline_html.egg-info/entry_points.txt
inline_html.egg-info/requires.txt
inline_html.egg-info/top_level.txt