Metadata-Version: 1.2
Name: inline-html
Version: 1.0.0
Summary: HTML stylesheet inliner, replaces resources with data-uri
Home-page: https://github.com/zopyx/inline-html
Author: Andreas Jung
Author-email: info@zopyx.com
Maintainer: Andreas Jung
Maintainer-email: info@zopyx.com
License: GPL2
Keywords: DocRaptor,HTML,CSS,DATA-URI
Platform: UNKNOWN
Classifier: Environment :: Web Environment
Classifier: Intended Audience :: Developers
Classifier: Intended Audience :: Information Technology
Classifier: Topic :: Text Processing :: Markup :: HTML
